freemt_utils/__init__.py
freemt_utils/arun.py
freemt_utils/cos_matrix2.py
freemt_utils/httpx_get.py
freemt_utils/langcode_to_tmxcode.py
freemt_utils/logger_level.py
freemt_utils/make_url.py
freemt_utils/mtok.py
freemt_utils/report_time.py
freemt_utils/save_tempfile.py
freemt_utils/spinner.py
freemt_utils/switch_to.py
freemt_utils/with_func_attrs.py
freemt_utils-0.1.1.dist-info/LICENSE
freemt_utils-0.1.1.dist-info/METADATA
freemt_utils-0.1.1.dist-info/WHEEL
freemt_utils-0.1.1.dist-info/top_level.txt
freemt_utils-0.1.1.dist-info/RECORD
