Metadata-Version: 2.1
Name: freemt-utils
Version: 0.1.1
Summary: baidu translate for free with async and proxy support
Home-page: http://github.com/ffreemt/freemt-utils
Author: mikeee
License: MIT License
Download-URL: https://github.com/ffreemt/freemt-utils/archive/v_011.tar.gz
Keywords: machine translation,free,sign
Platform: UNKNOWN
Classifier: Development Status :: 3 - Alpha
Classifier: Intended Audience :: Developers
Classifier: Programming Language :: Python :: 3
Classifier: Programming Language :: Python :: 3.6
Classifier: License :: OSI Approved :: MIT License
Requires-Dist: httpx
Requires-Dist: tqdm
Requires-Dist: pytest
Requires-Dist: logzero
Requires-Dist: sacremoses
Requires-Dist: numpy
Requires-Dist: marisa-trie
Requires-Dist: langcodes
Requires-Dist: chardet
